MANIFEST.in
README.rst
setup.py
docs/HISTORY.txt
docs/LICENSE.GPL
docs/LICENSE.txt
ftw/__init__.py
ftw.jsondump.egg-info/PKG-INFO
ftw.jsondump.egg-info/SOURCES.txt
ftw.jsondump.egg-info/dependency_links.txt
ftw.jsondump.egg-info/entry_points.txt
ftw.jsondump.egg-info/namespace_packages.txt
ftw.jsondump.egg-info/not-zip-safe
ftw.jsondump.egg-info/requires.txt
ftw.jsondump.egg-info/top_level.txt
ftw/jsondump/__init__.py
ftw/jsondump/configure.zcml
ftw/jsondump/directly_provided_interfaces.py
ftw/jsondump/interfaces.py
ftw/jsondump/localroles.py
ftw/jsondump/metadata.py
ftw/jsondump/properties.py
ftw/jsondump/representation.py
ftw/jsondump/testing.py
ftw/jsondump/uid.py
ftw/jsondump/workflow.py
ftw/jsondump/archetypes/__init__.py
ftw/jsondump/archetypes/base_fields.py
ftw/jsondump/archetypes/configure.zcml
ftw/jsondump/archetypes/date_field.py
ftw/jsondump/archetypes/fields.py
ftw/jsondump/archetypes/file_field.py
ftw/jsondump/archetypes/lines_field.py
ftw/jsondump/archetypes/reference_field.py
ftw/jsondump/archetypes/text_field.py
ftw/jsondump/dexterity/__init__.py
ftw/jsondump/dexterity/base.py
ftw/jsondump/dexterity/configure.zcml
ftw/jsondump/dexterity/datetime.py
ftw/jsondump/dexterity/fields.py
ftw/jsondump/dexterity/namedfile.py
ftw/jsondump/dexterity/richtext.py
ftw/jsondump/tests/__init__.py
ftw/jsondump/tests/base.py
ftw/jsondump/tests/builders.py
ftw/jsondump/tests/dxitem.py
ftw/jsondump/tests/extender.py
ftw/jsondump/tests/helpers.py
ftw/jsondump/tests/test_archetypes_fields.py
ftw/jsondump/tests/test_archetypes_partial.py
ftw/jsondump/tests/test_dexterity_fields.py
ftw/jsondump/tests/test_file_callback.py
ftw/jsondump/tests/test_interfaces_partial.py
ftw/jsondump/tests/test_localroles_partial.py
ftw/jsondump/tests/test_metadata_partial.py
ftw/jsondump/tests/test_properties_partial.py
ftw/jsondump/tests/test_representation.py
ftw/jsondump/tests/test_uid_partial.py
ftw/jsondump/tests/test_workflows_partial.py
ftw/jsondump/tests/tests.zcml
ftw/jsondump/tests/assets/archetypes_document.json
ftw/jsondump/tests/assets/dexterity_item.json
ftw/jsondump/tests/assets/empty.gif
ftw/jsondump/tests/assets/helloworld.py
ftw/jsondump/tests/profiles/integration/metadata.xml
ftw/jsondump/tests/profiles/integration/types.xml
